[
  {
    "publishedfileid": "3617161583",
    "title": "Convenient Cabinet Action",
    "file_description": "Added several cabinet actions, each unlocked by different technologies from Era 1 to Era 5. Please check the specific unlocking technologies in the game.",
    "preview_url": 	"https://images.steamusercontent.com/ugc/17402062966084202718/43387FDFEFE18731F716A6AECADCD9FC0230985F/",
    "time_updated": "1766928675",
    "download_link": "https://cold-eu-agl-1.gofile.io/download/direct/a35679aa-5121-4157-83c5-48bc5cbbb6b5/3634230997%20-%20Interloper%20Multiplayer%20Mod.7z"
  },
  {
    "publishedfileid": "3612931313",
    "title": "Faster Seige",
    "file_description": "-",
    "preview_url": 	"https://images.steamusercontent.com/ugc/14828046762933153467/9BD2523B3F4EA2B35A3721C1A98A3D3B39593203/",
    "time_updated": "1767463256",
    "download_link": "https://cold-eu-agl-1.gofile.io/download/direct/8718db58-4f57-47bc-9814-66a61f5defe8/3612931313%20-%20Faster%20Seige.7z"
  }
]
